color_selector/__init__.py
color_selector/frontend/.env
color_selector/frontend/.prettierrc
color_selector/frontend/index.html
color_selector/frontend/package-lock.json
color_selector/frontend/package.json
color_selector/frontend/tsconfig.json
color_selector/frontend/vite.config.ts
color_selector/frontend/build_copy/bootstrap.min.css
color_selector/frontend/build_copy/index.html
color_selector/frontend/build_copy/assets/index-BOhR8CfJ.js
color_selector/frontend/public/bootstrap.min.css
color_selector/frontend/src/MyComponent.tsx
color_selector/frontend/src/index.tsx
color_selector/frontend/src/vite-env.d.ts
color_selector-0.1.0.dist-info/METADATA
color_selector-0.1.0.dist-info/WHEEL
color_selector-0.1.0.dist-info/licenses/LICENSE
color_selector-0.1.0.dist-info/RECORD
