Metadata-Version: 2.4
Name: color-selector
Version: 0.1.0
Summary: Streamlit component for color selection with support for solid colors and gradients
Project-URL: Homepage, https://github.com/seu-usuario/color-selector
Project-URL: Repository, https://github.com/seu-usuario/color-selector
Project-URL: Issues, https://github.com/seu-usuario/color-selector/issues
Author-email: Seu Nome <seu.email@exemplo.com>
Maintainer-email: Seu Nome <seu.email@exemplo.com>
License: MIT
License-File: LICENSE
Keywords: color,component,gradient,selector,streamlit,visualization
Classifier: Development Status :: 4 - Beta
Classifier: Intended Audience :: Developers
Classifier: License :: OSI Approved :: MIT License
Classifier: Programming Language :: Python :: 3
Classifier: Programming Language :: Python :: 3.7
Classifier: Programming Language :: Python :: 3.8
Classifier: Programming Language :: Python :: 3.9
Classifier: Programming Language :: Python :: 3.10
Classifier: Programming Language :: Python :: 3.11
Classifier: Topic :: Scientific/Engineering :: Visualization
Classifier: Topic :: Software Development :: Libraries :: Python Modules
Requires-Python: >=3.7
Requires-Dist: streamlit>=0.63
Provides-Extra: devel
Requires-Dist: playwright==1.48.0; extra == 'devel'
Requires-Dist: pytest-playwright-snapshot==1.0; extra == 'devel'
Requires-Dist: pytest-rerunfailures==12.0; extra == 'devel'
Requires-Dist: pytest==7.4.0; extra == 'devel'
Requires-Dist: requests==2.31.0; extra == 'devel'
Requires-Dist: wheel; extra == 'devel'
